{
  "name": "MBNetwork",
  "version": "0.1.0",
  "summary": "MBNetwork - Network request can be easier",
  "description": "MBNetwork is an network request framework based on Alamofire and ObjectMapper, aiming at making network request easier",
  "homepage": "https://github.com/mmoaay/MBNetwork",
  "license": {
    "type": "MIT",
    "file": "LICENSE"
  },
  "authors": {
    "mmoaay": "mmoaay@sina.com"
  },
  "source": {
    "git": "https://github.com/mmoaay/MBNetwork.git",
    "tag": "0.1.0"
  },
  "platforms": {
    "ios": "8.0"
  },
  "source_files": "MBNetwork/Classes/**/*",
  "resources": "MBNetwork/Assets/**/*",
  "dependencies": {
    "Alamofire": [
      "~>4"
    ],
    "SwiftProtobuf": [

    ],
    "AlamofireObjectMapper": [

    ]
  },
  "pushed_with_swift_version": "3.0"
}
