{
  "name": "WFNetwork",
  "version": "1.0.0",
  "summary": "WFNetwork is a network module that used in WangFan App.",
  "description": "WFNetwork is a network module that used for WangFan App.It's based on AFNetwork.",
  "homepage": "http://git.ihangmei.com/caolongyao/WFNetwork",
  "license": {
    "type": "MIT",
    "file": "LICENSE"
  },
  "authors": {
    "caolongyao": "caolongyao@ihangmei.com"
  },
  "source": {
    "git": "http://git.ihangmei.com/caolongyao/WFNetwork.git",
    "tag": "1.0.0"
  },
  "platforms": {
    "ios": "7.0"
  },
  "source_files": "WFNetwork/Classes/**/*",
  "dependencies": {
    "AFNetworking": [
      "~> 3.0"
    ]
  }
}
