{
  "name": "CMYBaseLib",
  "version": "0.1.0",
  "summary": "一个牛逼的项目",
  "description": "TODO: Add long description of the pod here.",
  "homepage": "https://github.com/changwuguo/CwgTestLib",
  "license": {
    "type": "MIT",
    "file": "LICENSE"
  },
  "authors": {
    "changwuguo": "changwuguo@qq.com"
  },
  "source": {
    "git": "https://github.com/changwuguo/CwgTestLib.git",
    "tag": "0.1.0"
  },
  "platforms": {
    "ios": "9.0"
  },
  "source_files": "CMYBaseLib/Classes/**/*",
  "dependencies": {
    "AFNetworking": [
      "~> 2.3"
    ]
  }
}
