{
  "name": "Huahuapd",
  "version": "0.2.1",
  "summary": "A new Huahuapd.",
  "description": "Huahuapd",
  "homepage": "http://keaipi.com",
  "license": {
    "file": "../LICENSE"
  },
  "authors": {
    "Your Company": "email@keaipi.com"
  },
  "source": {
    "http": "https://ning88.oss-cn-qingdao.aliyuncs.com/huahua.zip",
    "type": "zip"
  },
  "swift_versions": "5.0",
  "platforms": {
    "ios": "12.2"
  },
  "requires_arc": true,
  "pod_target_xcconfig": {
    "VALID_ARCHS": "x86_64 armv7 arm64"
  },
  "vendored_frameworks": "huahua/Release/*",
  "dependencies": {
    "AliPlayerSDK_iOS": [
      "5.4.9.1-26507944"
    ],
    "GDTMobSDK": [
      "4.14.02"
    ],
    "Ads-CN-Beta": [
      "5.0.0.1"
    ],
    "UMCommon": [

    ],
    "UMDevice": [

    ],
    "FMDB": [

    ],
    "MJExtension": [

    ],
    "OrderedSet": [

    ]
  },
  "swift_version": "5.0"
}
