{
  "name": "NSObjectCoder",
  "version": "1.0",
  "summary": "NSObjectCoder is an efficient library that automatically encodes and decodes all attributes of NSObject instance.",
  "homepage": "https://github.com/Eric-LeiYang/NSObjectCoder",
  "license": {
    "type": "MIT"
  },
  "authors": {
    "Eric-LeiYang": "yanglei.eric@gmail.com"
  },
  "source": {
    "git": "https://github.com/Eric-LeiYang/NSObjectCoder.git",
    "tag": "1.0"
  },
  "source_files": "NSObjectCoder/NSObjectCoder/NSObjectCoder/NSObjectCoder.{h,m}",
  "requires_arc": true
}
