{
  "name": "SPLFormular",
  "version": "0.2.0",
  "summary": "Simply dynamic formulars, backed by SPLTableViewBehavior.",
  "homepage": "https://github.com/OliverLetterer/SPLFormular",
  "license": "MIT",
  "authors": {
    "Oliver Letterer": "oliver.letterer@gmail.com"
  },
  "source": {
    "git": "https://github.com/OliverLetterer/SPLFormular.git",
    "tag": "0.2.0"
  },
  "social_media_url": "https://twitter.com/oletterer",
  "platforms": {
    "ios": "8.0"
  },
  "requires_arc": true,
  "source_files": [
    "SPLFormular",
    "SPLFormular/Private"
  ],
  "private_header_files": "SPLFormular/Private/*.h",
  "dependencies": {
    "SPLTableViewBehavior": [
      "~> 0.7.0"
    ]
  }
}
