{
  "name": "TripKitInterApp",
  "version": "4.1.0",
  "summary": "Add-ons to SkedGo's TripKit",
  "homepage": "https://github.com/skedgo/tripkit-ios",
  "license": {
    "type": "Apache-2.0",
    "file": "LICENSE"
  },
  "authors": {
    "Adrian Schoenig": "adrian@skedgo.com"
  },
  "source": {
    "git": "https://github.com/skedgo/tripkit-ios.git",
    "tag": "4.1.0"
  },
  "swift_versions": "5.5",
  "platforms": {
    "ios": "13.0"
  },
  "requires_arc": true,
  "dependencies": {
    "TripKit": [
      "~> 4.1.0"
    ]
  },
  "source_files": "Sources/TripKitInterApp/**/*.{swift}",
  "swift_version": "5.5"
}
