{
  "name": "testpody",
  "version": "0.1.1",
  "summary": "test pod used to test integration",
  "description": "TODO: Add long description of the pod here.",
  "homepage": "https://github.com/umairyousafte/testpod",
  "license": {
    "type": "MIT",
    "file": "LICENSE"
  },
  "authors": {
    "umairyousafte": "umair.y@theentertainerasia.com"
  },
  "source": {
    "git": "https://github.com/umairyousafte/testpod.git",
    "tag": "0.1.1"
  },
  "platforms": {
    "ios": "10.0"
  },
  "swift_versions": "5.0",
  "source_files": "testpody/Classes/**/*",
  "swift_version": "5.0"
}
