{
  "name": "GkashPayment",
  "version": "0.2",
  "license": "MIT",
  "homepage": "https://github.com/gkashmy/gkash-ios-sdk",
  "authors": {
    "Gkash developer": "developers@gkash.com"
  },
  "summary": "This library allows you to integrate Gkash Payment Gateway into your IOS App.",
  "source": {
    "git": "https://github.com/gkashmy/gkash-ios-sdk.git",
    "tag": "0.2"
  },
  "source_files": "GkashPayment/*.swift",
  "swift_versions": "5.0",
  "platforms": {
    "ios": "14.0"
  },
  "swift_version": "5.0"
}
