{
  "name": "JukkoSdk",
  "version": "1.0.0",
  "summary": "JukkoSdk is a framework to show adverts to user within your app.",
  "description": "JukkoSdk is Swift iOS framework to show adverts to user. Supports Unity and native iOS apps.",
  "homepage": "http://example.com/",
  "license": {
    "type": "Private",
    "text": "see jukko.com for license info"
  },
  "authors": {
    "Jukko": "devs@jukko.com"
  },
  "platforms": {
    "ios": "10.0"
  },
  "source": {
    "http": "https://dl.staging.jukko.com/ios-sdk/staging/JukkoSdk-staging-1.0.0.framework.zip"
  },
  "ios": {
    "vendored_frameworks": "JukkoSdk.framework"
  },
  "pod_target_xcconfig": {
    "SWIFT_VERSION": "3.0"
  }
}
