{
  "name": "Cocoa-SPM",
  "version": "2.0.0",
  "summary": "Dependency available in Cocoa-SPM.",
  "description": "TODO: Add long description of the pod here.",
  "homepage": "https://github.com/LoydAntony/Cocoa-SPM",
  "license": {
    "type": "MIT",
    "file": "LICENSE"
  },
  "authors": {
    "LoydAntony": "lrebeiro.consultant@newscorp.com"
  },
  "source": {
    "git": "https://github.com/LoydAntony/Cocoa-SPM.git",
    "tag": "2.0.0"
  },
  "platforms": {
    "ios": "10.0"
  },
  "source_files": "Cocoa-SPM/*",
  "subspecs": [
    {
      "name": "Basic",
      "source_files": "Cocoa-SPM/Basic/**/*"
    },
    {
      "name": "Ads",
      "source_files": "Cocoa-SPM/Ads/**/*",
      "dependencies": {
        "Cocoa-SPM/Basic": [

        ]
      }
    },
    {
      "name": "Casting",
      "source_files": "Cocoa-SPM/Casting/**/*",
      "dependencies": {
        "Cocoa-SPM/Basic": [

        ]
      }
    }
  ]
}
