{
  "name": "GlobeConnectSwift",
  "version": "1.2.0",
  "summary": "Globe Connect for Swift.",
  "description": "Globe Connect for Swift platform provides an implementation of Globe APIs e.g Authentication, Amax, Sms etc. that is easy to use and can be integrated in your existing Swift application. Below shows some samples on how to use the API depending on the functionality that you need to integrate in your application.",
  "homepage": "http://www.globelabs.com.ph",
  "license": {
    "type": "MIT",
    "file": "LICENSE"
  },
  "authors": {
    "Rico Maglayon": "rmaglayon@gmail.com"
  },
  "platforms": {
    "ios": "10.0"
  },
  "source": {
    "git": "https://github.com/globelabs/globe-connect-swift.git",
    "tag": "1.2.0"
  },
  "source_files": "Sources/*.swift",
  "exclude_files": "Classes/Exclude",
  "pushed_with_swift_version": "3.0"
}
