{
  "name": "jooohhn-Amplitude",
  "version": "9.3.3",
  "summary": "Amplitude iOS/tvOS/macOS SDK.",
  "homepage": "https://amplitude.com",
  "license": {
    "type": "MIT"
  },
  "authors": {
    "jooohhn": "john.tran@amplitude.com"
  },
  "source": {
    "git": "https://github.com/jooohhn/Amplitude-iOS.git",
    "tag": "v9.3.3"
  },
  "requires_arc": true,
  "libraries": "sqlite3.0",
  "platforms": {
    "ios": "10.0",
    "tvos": "9.0",
    "osx": "10.10"
  },
  "ios": {
    "source_files": "Sources/Amplitude/*.{h,m}",
    "resources": "Sources/Amplitude/**/*.{der,xib,png}"
  },
  "tvos": {
    "source_files": "Sources/Amplitude/*.{h,m}",
    "resources": "Sources/Amplitude/**/*.{der}",
    "exclude_files": [
      "Sources/Amplitude/AMPBubbleView.{h,m}",
      "Sources/Amplitude/AMPEventExplorer.{h,m}",
      "Sources/Amplitude/AMPInfoViewController.{h,m}"
    ]
  },
  "osx": {
    "source_files": "Sources/Amplitude/*.{h,m}",
    "resources": "Sources/Amplitude/**/*.{der}",
    "exclude_files": [
      "Sources/Amplitude/AMPBubbleView.{h,m}",
      "Sources/Amplitude/AMPEventExplorer.{h,m}",
      "Sources/Amplitude/AMPInfoViewController.{h,m}"
    ]
  }
}
