{
  "name": "MemojiView",
  "version": "0.0.1",
  "summary": "Retrieve and display the users memoji",
  "homepage": "https://github.com/emrearmagan/MemojiView",
  "license": {
    "type": "MIT",
    "file": "LICENSE"
  },
  "authors": {
    "Emre Armagan": "emrearmagan.dev@gmail.com"
  },
  "source": {
    "git": "https://github.com/emrearmagan/MemojiView.git",
    "tag": "0.0.1"
  },
  "swift_versions": "5.0",
  "platforms": {
    "ios": "12.0"
  },
  "source_files": "MemojiView/**/*",
  "swift_version": "5.0"
}
