{
  "name": "MSPMolocoAdapter",
  "summary": "an adapter for Moloco SDK",
  "description": "an adapter for Moloco SDK",
  "homepage": "https://github.com/ParticleMedia/msp-ios-sdk-public",
  "license": "Copyright",
  "authors": {
    "Mingming Luo": "mingming.luo@newsbreak.com"
  },
  "platforms": {
    "ios": "15.0"
  },
  "swift_versions": "5.0",
  "requires_arc": true,
  "static_framework": true,
  "pod_target_xcconfig": {
    "SWIFT_INCLUDE_PATHS": "$(inherited) $(PODS_CONFIGURATION_BUILD_DIR)",
    "VALID_ARCHS": "x86_64 armv7 arm64",
    "DEFINES_MODULE": "YES"
  },
  "user_target_xcconfig": {
    "SWIFT_INCLUDE_PATHS": "$(inherited) $(PODS_CONFIGURATION_BUILD_DIR)",
    "EXCLUDED_ARCHS[sdk=iphonesimulator*]": "arm64"
  },
  "dependencies": {
    "MolocoSDKiOS": [

    ],
    "MSPSharedLibraries": [
      "1.1.0-rc.0"
    ],
    "MSPiOSCore": [
      "1.1.0-rc.0"
    ]
  },
  "version": "1.1.0-rc.0",
  "source": {
    "http": "https://github.com/ParticleMedia/msp-ios-sdk-public/releases/download/1.1.0-rc.0/MSPMolocoAdapter-1.1.0-rc.0.zip",
    "type": "zip",
    "sha256": "88772e3c044842a08646e53a8b355cdcff26fc4adc2d47492807fc39dc7b023f"
  },
  "vendored_frameworks": "Binary/MSPMolocoAdapter.xcframework",
  "swift_version": "5.0"
}
