{
  "name": "Smooch",
  "version": "10.1.0",
  "summary": "Build customer relationships that last",
  "description": "Smooch lets you have rich conversations with your users, right in your app or on your website.",
  "homepage": "http://smooch.io",
  "license": {
    "type": "Commercial",
    "text": "Smooch Technologies Inc.  All rights reserved."
  },
  "authors": {
    "Smooch Technologies Inc.": "help@smooch.io"
  },
  "source": {
    "git": "https://github.com/zendesk/sunshine-conversations-ios.git",
    "tag": "10.1.0"
  },
  "preserve_paths": "Smooch.xcframework/*",
  "frameworks": [
    "Smooch",
    "CoreText",
    "SystemConfiguration",
    "CoreTelephony",
    "Foundation",
    "CoreGraphics",
    "UIKit",
    "QuartzCore",
    "AssetsLibrary",
    "Photos",
    "AVFoundation",
    "CFNetwork"
  ],
  "libraries": "icucore",
  "xcconfig": {
    "FRAMEWORK_SEARCH_PATHS": "$(PODS_ROOT)/Smooch"
  },
  "vendored_frameworks": "Smooch.xcframework",
  "requires_arc": true,
  "platforms": {
    "ios": "8.0"
  }
}
