{
  "name": "OctagonAnalyticsService",
  "version": "1.7.2",
  "summary": "OctagonAnalyticsService - API provider for iOS.",
  "description": "OctagonAnalyticsService - Kibana API service provider for iOS application.\nKibana is a trademark of Elasticsearch BV, registered in the US and in other countries.",
  "homepage": "https://gitlab.g42.ae/pax-z100/marble/mobile/ios/octagonanalyticsservice",
  "license": {
    "type": "MIT",
    "file": "LICENSE"
  },
  "authors": {
    "OctagonMobile": "G42-Analytics"
  },
  "source": {
    "git": "https://gitlab.g42.ae/pax-z100/marble/mobile/ios/octagonanalyticsservice.git",
    "tag": "1.7.2"
  },
  "platforms": {
    "ios": "13.0"
  },
  "swift_versions": "5.0",
  "source_files": "OctagonAnalyticsService/Classes/**/*",
  "dependencies": {
    "Alamofire": [

    ],
    "SwiftDate": [

    ]
  },
  "swift_version": "5.0"
}
