{
  "name": "MS_ScrollView",
  "version": "0.1.2",
  "summary": "The easiest way to use pull-to-refresh with Swift2.0 program language.",
  "homepage": "https://github.com/yuanshuainiuniu/AdvertisingScrollView-banner",
  "license": "MIT",
  "authors": {
    "yuanshuai": "717999274@qq.com"
  },
  "platforms": {
    "ios": "7.0"
  },
  "source": {
    "git": "https://github.com/yuanshuainiuniu/AdvertisingScrollView-banner.git",
    "tag": "0.1.2"
  },
  "source_files": "MSScrollViewLib/**/*.{h,m}",
  "resources": "MSScrollViewLib/MSSource.bundle",
  "requires_arc": true
}
