{
  "name": "HLPods",
  "version": "1.0.0",
  "summary": "HLPods.",
  "description": "\"The first cocopodDemo\"",
  "homepage": "https://github.com/hailong123/HLPod.git",
  "license": {
    "type": "MIT"
  },
  "authors": {
    "SeaDragon": "hailong_hl@163.com"
  },
  "source": {
    "git": "https://github.com/hailong123/HLPod.git",
    "tag": "1.0.0"
  },
  "source_files": [
    "HLPods",
    "HLPods/*.{h,m}"
  ],
  "exclude_files": "Classes/Exclude",
  "platforms": {
    "osx": null,
    "ios": null,
    "tvos": null,
    "watchos": null
  },
  "deprecated": true
}
