{
  "name": "ZJRoutes",
  "version": "0.0.3",
  "summary": "ZJRoutes轻量路由框架、ZJMediator中间件",
  "description": "TODO: ZJRoutes一个简单的路由框架、ZJMediator跳转中间件.",
  "homepage": "https://github.com/zhuzhuxingtianxia/ZJRoutes",
  "license": {
    "type": "MIT",
    "file": "LICENSE"
  },
  "authors": {
    "ZJ": "873391579@qq.com"
  },
  "source": {
    "git": "https://github.com/zhuzhuxingtianxia/ZJRoutes.git",
    "tag": "0.0.3"
  },
  "platforms": {
    "ios": "8.0"
  },
  "source_files": "ZJRoutes/Classes/**/*"
}
