{
  "name": "CHSDK",
  "version": "0.1.5",
  "summary": "CHSDK, CHSDK.",
  "description": "CHSDK, CHSDK, CHSDK, CHSDK.",
  "homepage": "https://github.com/wang-chuanhui/CHSDK",
  "license": {
    "type": "MIT",
    "file": "LICENSE"
  },
  "authors": {
    "372020909@qq.com": "372020909@qq.com"
  },
  "source": {
    "git": "https://github.com/wang-chuanhui/CHSDK.git",
    "tag": "0.1.5"
  },
  "swift_version": "4.0",
  "platforms": {
    "ios": "10.0"
  },
  "subspecs": [
    {
      "name": "MulticastDelegate",
      "source_files": "CHSDK/Classes/MulticastDelegate/**/*"
    },
    {
      "name": "ScanCode",
      "source_files": "CHSDK/Classes/ScanCode/**/*",
      "resource_bundles": {
        "CHScanCode": [
          "CHSDK/Assets/ScanCode/*.png",
          "CHSDK/Resources/ScanCode/**/*"
        ]
      }
    },
    {
      "name": "NibDesignable",
      "source_files": "CHSDK/Classes/NibDesignable/**/*"
    },
    {
      "name": "Observer",
      "source_files": "CHSDK/Classes/Observer/**/*"
    }
  ]
}
