{
  "name": "WTCarouselFlowLayout",
  "version": "0.1.0",
  "summary": "To use collectView show carousel list.",
  "description": "WTCarouselFlowLayout one kind of collectView layout to show carousel list.",
  "homepage": "https://github.com/wusuowei/WTCarouselFlowLayout",
  "license": {
    "type": "MIT",
    "file": "LICENSE"
  },
  "authors": {
    "wentianen": "1206860151@qq.com"
  },
  "source": {
    "git": "https://github.com/wusuowei/WTCarouselFlowLayout.git",
    "tag": "0.1.0"
  },
  "social_media_url": "http://www.jianshu.com/u/d83ef9913d22",
  "platforms": {
    "ios": "8.0"
  },
  "source_files": "WTCarouselFlowLayout/Classes/**/*",
  "pushed_with_swift_version": "3.0"
}
