{
  "name": "LwayveSDK",
  "version": "1.2.0",
  "summary": "iOS library",
  "homepage": "https://github.com/LWAYVE/ios-sdk",
  "authors": {
    "Lixar, Inc": "infra@lwayve.com"
  },
  "platforms": {
    "ios": "9.0"
  },
  "source": {
    "git": "https://github.com/LWAYVE/ios-sdk.git",
    "tag": "1.2.0"
  },
  "vendored_frameworks": "LwayveSDK/LwayveSDK.framework",
  "frameworks": "Foundation",
  "dependencies": {
    "YapDatabase": [
      "3.0"
    ],
    "Alamofire": [
      "~> 4.5.0"
    ],
    "SwiftyJSON": [
      "~> 3.1.4"
    ],
    "KeychainSwift": [
      "~> 8.0.2"
    ],
    "CocoaLumberjack": [
      "~> 3.2.0"
    ],
    "FirebaseMessaging": [
      "2.0.0"
    ]
  },
  "requires_arc": true,
  "license": "MIT",
  "pushed_with_swift_version": "3.0"
}
