{
  "name": "sdl-rkx",
  "version": "0.1.0",
  "summary": "SDL visual surveys for ResearchKit",
  "description": "The Small Data Lab ResearchKit Extensions package is the easiest way to include SDL visual surveys (YADL, MEDL, PAM) into a ResearchKit application.",
  "homepage": "https://github.com/cornelltech/sdl-rkx",
  "license": "MIT",
  "authors": {
    "James Kizer, Cornell Tech Foundry": "jdk288 at cornell dot edu"
  },
  "source": {
    "git": "https://github.com/cornelltech/sdl-rkx.git",
    "tag": "0.1.0"
  },
  "platforms": {
    "ios": "9.0"
  },
  "source_files": "sdl-rkx/Classes/**/*",
  "resources": [
    "sdl-rkx/Assets/PAM.xcassets",
    "sdl-rkx/Assets/PAM.json"
  ],
  "dependencies": {
    "ResearchKit": [
      "~> 1.3.1"
    ]
  }
}
