{
  "name": "custom_uiview",
  "version": "0.1.0",
  "summary": "A customizable UIView with corner radius, borders and shadows.",
  "description": "custom_uiview is a lightweight Swift library that provides an easy-to-use\nUIView subclass for rounded corners, borders, shadows, and customizable UI elements.\nPerfect for creating clean and reusable UI components in iOS apps.",
  "homepage": "https://github.com/ashishtukadia/custom_uiview",
  "license": {
    "type": "MIT",
    "file": "LICENSE"
  },
  "authors": {
    "AshishT": "ashishtukadia3609@gmail.com"
  },
  "source": {
    "git": "https://github.com/ashishtukadia/custom_uiview.git"
  },
  "platforms": {
    "ios": "10.0"
  },
  "swift_versions": "5.0",
  "source_files": "custom_uiview/Classes/**/*",
  "swift_version": "5.0"
}
