{
  "name": "WebViewCapture",
  "version": "0.1.0",
  "summary": "Make a snapshot of a web document element",
  "description": "WKWebView extension to take a snapshot image with specific element.",
  "homepage": "https://github.com/ssauma/WebViewCapture",
  "license": {
    "type": "MIT",
    "file": "LICENSE"
  },
  "authors": {
    "Juyeon Lee": "juyeonlee@me.com"
  },
  "source": {
    "git": "https://github.com/ssauma/WebViewCapture.git",
    "tag": "0.1.0"
  },
  "platforms": {
    "ios": "11.0"
  },
  "source_files": "WebViewCapture/Classes/**/*",
  "swift_versions": "5.0",
  "swift_version": "5.0"
}
