{
  "name": "KJNetworkPlugin",
  "version": "1.0.16",
  "summary": "A Network Plugin With AFNetworking.",
  "homepage": "https://github.com/yangKJ/KJNetworkPlugin",
  "license": "MIT",
  "authors": {
    "77": "ykj310@126.com"
  },
  "source": {
    "git": "https://github.com/yangKJ/KJNetworkPlugin.git",
    "tag": "1.0.16"
  },
  "platforms": {
    "ios": "9.0"
  },
  "swift_versions": "5.0",
  "requires_arc": true,
  "static_framework": true,
  "subspecs": [
    {
      "name": "Network",
      "source_files": "NetworkPlugin/Network/*.{h,m}",
      "dependencies": {
        "AFNetworking": [
          "~> 4.0.0"
        ]
      }
    },
    {
      "name": "Manager",
      "source_files": "NetworkPlugin/Manager/*.{h,m}",
      "dependencies": {
        "KJNetworkPlugin/Network": [

        ]
      }
    },
    {
      "name": "Batch",
      "source_files": "NetworkPlugin/Batch/*.{h,m}",
      "dependencies": {
        "KJNetworkPlugin/Network": [

        ]
      }
    },
    {
      "name": "Chain",
      "source_files": "NetworkPlugin/Chain/*.{h,m}",
      "dependencies": {
        "KJNetworkPlugin/Network": [

        ]
      }
    },
    {
      "name": "Base",
      "source_files": "NetworkPlugin/Plugins/Base/*.{h,m}",
      "prefix_header_contents": "#import \"KJNetworkPlugin-Bridging-Header.h\"",
      "dependencies": {
        "KJNetworkPlugin/Network": [

        ]
      }
    },
    {
      "name": "Thief",
      "source_files": "NetworkPlugin/Plugins/Thief/*.{h,m}",
      "dependencies": {
        "KJNetworkPlugin/Base": [

        ]
      }
    },
    {
      "name": "Certificate",
      "source_files": "NetworkPlugin/Plugins/Certificate/*.{h,m}",
      "dependencies": {
        "KJNetworkPlugin/Base": [

        ]
      }
    },
    {
      "name": "Cache",
      "source_files": "NetworkPlugin/Plugins/Cache/*.{h,m}",
      "dependencies": {
        "KJNetworkPlugin/Base": [

        ],
        "YYCache": [
          "~> 1.0.4"
        ]
      }
    },
    {
      "name": "Anslysis",
      "source_files": "NetworkPlugin/Plugins/Anslysis/*.{h,m}",
      "dependencies": {
        "KJNetworkPlugin/Base": [

        ],
        "MJExtension": [
          "~> 3.3.0"
        ]
      }
    },
    {
      "name": "Loading",
      "source_files": "NetworkPlugin/Plugins/Loading/*.{h,m}",
      "dependencies": {
        "KJNetworkPlugin/Base": [

        ],
        "MBProgressHUD": [
          "~> 1.2.0"
        ]
      }
    },
    {
      "name": "Capture",
      "source_files": "NetworkPlugin/Plugins/Capture/*.{h,m}",
      "dependencies": {
        "KJNetworkPlugin/Base": [

        ],
        "MJExtension": [
          "~> 3.3.0"
        ]
      }
    },
    {
      "name": "Code",
      "source_files": "NetworkPlugin/Plugins/Code/*.{h,m}",
      "dependencies": {
        "KJNetworkPlugin/Base": [

        ]
      }
    },
    {
      "name": "Refresh",
      "source_files": "NetworkPlugin/Plugins/Refresh/*.{h,m}",
      "dependencies": {
        "KJNetworkPlugin/Base": [

        ]
      }
    },
    {
      "name": "Indicator",
      "source_files": "NetworkPlugin/Plugins/Indicator/*.swift",
      "dependencies": {
        "KJNetworkPlugin/Base": [

        ]
      }
    },
    {
      "name": "Warning",
      "source_files": "NetworkPlugin/Plugins/Warning/*.swift",
      "dependencies": {
        "KJNetworkPlugin/Base": [

        ],
        "Toast-Swift": [

        ]
      }
    }
  ],
  "swift_version": "5.0"
}
