{
  "name": "JRCommonShare",
  "version": "0.0.1",
  "summary": "A short description of JRShare.",
  "description": "TODO: Add long description of the pod here.",
  "homepage": "https://github.com/Cone1989/JRShare",
  "license": {
    "type": "MIT",
    "file": "LICENSE"
  },
  "authors": {
    "liqiang": "liqiang38@58.com"
  },
  "source": {
    "git": "https://github.com/Cone1989/JRShare.git",
    "tag": "0.0.1"
  },
  "platforms": {
    "ios": "8.0"
  },
  "frameworks": [
    "SystemConfiguration",
    "CoreTelephony"
  ],
  "libraries": [
    "c++",
    "z",
    "sqlite3.0"
  ],
  "requires_arc": true,
  "xcconfig": {
    "OTHER_LDFLAGS": "-ObjC"
  },
  "subspecs": [
    {
      "name": "Share",
      "source_files": "JRCommonShare/Classes/share/**/*"
    },
    {
      "name": "QQ",
      "source_files": "JRCommonShare/Classes/qq/**/*",
      "dependencies": {
        "JRCommonShare/Share": [

        ]
      },
      "vendored_frameworks": "JRCommonShare/Classes/qq/sdk/*.{framework}"
    },
    {
      "name": "Wechat",
      "source_files": "JRCommonShare/Classes/wechat/**/*",
      "dependencies": {
        "JRCommonShare/Share": [

        ]
      },
      "vendored_libraries": "JRCommonShare/Classes/wechat/sdk/*.{a}"
    }
  ]
}
